kolibri_zim_plugin/__init__.py
kolibri_zim_plugin/kolibri_plugin.py
kolibri_zim_plugin/root_urls.py
kolibri_zim_plugin/views.py
kolibri_zim_plugin/build/kolibri_zim_plugin.main_stats.json
kolibri_zim_plugin/static/kolibri_zim_plugin.main/kolibri_zim_plugin.main-1.4.0.js
kolibri_zim_plugin/static/kolibri_zim_plugin.main/kolibri_zim_plugin.main-1.4.0.js.map
kolibri_zim_plugin/static/kolibri_zim_plugin.main/kolibri_zim_plugin.main-1.4.1.js
kolibri_zim_plugin/static/kolibri_zim_plugin.main/kolibri_zim_plugin.main-1.4.1.js.map
kolibri_zim_plugin/static/kolibri_zim_plugin.main/kolibri_zim_plugin.main1.4.0.css
kolibri_zim_plugin/static/kolibri_zim_plugin.main/kolibri_zim_plugin.main1.4.0.rtl.css
kolibri_zim_plugin/static/kolibri_zim_plugin.main/kolibri_zim_plugin.main1.4.1.css
kolibri_zim_plugin/static/kolibri_zim_plugin.main/kolibri_zim_plugin.main1.4.1.rtl.css
kolibri_zim_plugin-1.4.2.dist-info/LICENSE
kolibri_zim_plugin-1.4.2.dist-info/METADATA
kolibri_zim_plugin-1.4.2.dist-info/WHEEL
kolibri_zim_plugin-1.4.2.dist-info/entry_points.txt
kolibri_zim_plugin-1.4.2.dist-info/top_level.txt
kolibri_zim_plugin-1.4.2.dist-info/RECORD
