Metadata-Version: 2.1
Name: kolibri-zim-plugin
Version: 1.4.2
Summary: Kolibri plugin to add a Zim file viewer
Home-page: https://github.com/endlessm/kolibri-zim-plugin
Author: Endless OS Foundation
Author-email: dylan@endlessos.org
License: MIT
Keywords: kolibri
Classifier: Development Status :: 2 - Pre-Alpha
Classifier: Intended Audience :: Developers
Classifier: License :: OSI Approved :: MIT License
Classifier: Natural Language :: English
Classifier: Programming Language :: Python :: 3
Classifier: Programming Language :: Python :: 3.4
Classifier: Programming Language :: Python :: 3.5
Classifier: Programming Language :: Python :: 3.6
Classifier: Programming Language :: Python :: 3.7
Classifier: Programming Language :: Python :: 3.8
Classifier: Programming Language :: Python :: Implementation :: PyPy
License-File: LICENSE
Requires-Dist: zimply-core (<2.0.0,>=1.0.4)
Provides-Extra: full
Requires-Dist: beautifulsoup4 (==4.11.1) ; extra == 'full'
Requires-Dist: lxml (==4.9.0) ; extra == 'full'
Provides-Extra: snippets
Requires-Dist: beautifulsoup4 (==4.11.1) ; extra == 'snippets'
